client_wars/__init__.py
client_wars/client.py
client_wars/config.py
client_wars/game.py
client_wars/map.py
client_wars/player.py
client_wars/tile.py
client_wars/websocket_updater.py
ClientWars-1.4.1.dist-info/LICENSE
ClientWars-1.4.1.dist-info/METADATA
ClientWars-1.4.1.dist-info/WHEEL
ClientWars-1.4.1.dist-info/top_level.txt
ClientWars-1.4.1.dist-info/RECORD
