Metadata-Version: 2.1
Name: ClientWars
Version: 1.4.1
Summary: War game, but for programmers.
Home-page: https://github.com/hvuhsg/ClientWars
Author: yoyo
Author-email: serverwars00@gmail.com
License: MIT
Keywords: game,war,programming,win,multiplayers
Platform: UNKNOWN
Classifier: Development Status :: 3 - Alpha
Classifier: Intended Audience :: Developers
Classifier: Topic :: Software Development :: Build Tools
Classifier: License :: OSI Approved :: MIT License
Classifier: Programming Language :: Python :: 3.6
Classifier: Programming Language :: Python :: 3.7
Classifier: Programming Language :: Python :: 3.8
Classifier: Programming Language :: Python :: 3.9
Requires-Dist: loguru
Requires-Dist: requests
Requires-Dist: websocket-client
